Metadata-Version: 1.1
Name: python-mauth
Version: 0.1.3
Summary: Mauth API client library
Home-page: UNKNOWN
Author: Webcase
Author-email: info@webcase.com.ua
License: UNKNOWN
Keywords: setup
Platform: UNKNOWN
Classifier: Development Status :: 1 - Beta
Classifier: Environment :: Console
Classifier: Environment :: Mauth
Classifier: Intended Audience :: Developers
Classifier: Operating System :: OS Independent
Classifier: Programming Language :: Python
